byu_pytest_utils/__init__.py
byu_pytest_utils/cpp_utils.py
byu_pytest_utils/decorators.py
byu_pytest_utils/dialog.py
byu_pytest_utils/edit_dist.py
byu_pytest_utils/html_comparison/__init__.py
byu_pytest_utils/html_comparison/comparator.py
byu_pytest_utils/html_comparison/extractor.py
byu_pytest_utils/html_comparison/gradescope.py
byu_pytest_utils/html_comparison/html_renderer.py
byu_pytest_utils/html_comparison/models.py
byu_pytest_utils/html_comparison/parser.py
byu_pytest_utils/html_comparison/renderers.py
byu_pytest_utils/html_comparison/template.css
byu_pytest_utils/html_comparison/template.html.jinja
byu_pytest_utils/popup.py
byu_pytest_utils/pytest_plugin.py
byu_pytest_utils/utils.py
byu_pytest_utils-0.8.0.dist-info/METADATA
byu_pytest_utils-0.8.0.dist-info/WHEEL
byu_pytest_utils-0.8.0.dist-info/entry_points.txt
byu_pytest_utils-0.8.0.dist-info/RECORD
