Metadata-Version: 2.4
Name: byu_pytest_utils
Version: 0.8.0
Summary: A few utilities for pytest to help with integration into gradescope
License: MIT
Author: Gordon Bean
Author-email: gbean@cs.byu.edu
Requires-Python: >=3.10,<4.0
Classifier: Framework :: Pytest
Classifier: License :: OSI Approved :: MIT License
Classifier: Programming Language :: Python :: 3
Classifier: Programming Language :: Python :: 3.10
Classifier: Programming Language :: Python :: 3.11
Classifier: Programming Language :: Python :: 3.12
Classifier: Programming Language :: Python :: 3.13
Classifier: Programming Language :: Python :: 3.14
Requires-Dist: beautifulsoup4 (>=4.14.2,<5.0.0)
Requires-Dist: jinja2 (>=3.1.6,<4.0.0)
Requires-Dist: pytest (>=9.0.1,<10.0.0)
